Metadata-Version: 1.1
Name: pypi-publisher
Version: 0.0.1
Summary: A cli for publishing packages to pypi, without the hassle
Home-page: https://github.com/wdm0006/ppp
Author: Will McGinnis
Author-email: will@pedalwrencher.com
License: BSD
Download-URL: https://github.com/wdm0006/ppp/tarball/0.0.1
Platform: UNKNOWN
Classifier: Development Status :: 3 - Alpha
Classifier: Intended Audience :: Developers
Classifier: Programming Language :: Python :: 3
